mvi/__init__.py
mvi/core.py
mvi/cli/__init__.py
mvi/cli/main.py
mvi_metrics-1.0.0.dist-info/METADATA
mvi_metrics-1.0.0.dist-info/WHEEL
mvi_metrics-1.0.0.dist-info/entry_points.txt
mvi_metrics-1.0.0.dist-info/top_level.txt
mvi_metrics-1.0.0.dist-info/RECORD
