Metadata-Version: 2.4
Name: mvi-metrics
Version: 1.0.0
Summary: Memory Vulnerability Index (MVI) for continual learning models
Author: Carla Centeno
License: MIT
Requires-Python: >=3.10
Requires-Dist: torch
Requires-Dist: numpy<2
